aresy/__init__.py
aresy-0.0.1.dist-info/LICENSE
aresy-0.0.1.dist-info/METADATA
aresy-0.0.1.dist-info/WHEEL
aresy-0.0.1.dist-info/top_level.txt
aresy-0.0.1.dist-info/RECORD
